st_img_selector/__init__.py
st_img_selector/example.py
st_img_selector/frontend/build/asset-manifest.json
st_img_selector/frontend/build/bootstrap.min.css
st_img_selector/frontend/build/index.html
st_img_selector/frontend/build/static/js/main.8bf4c404.js
st_img_selector/frontend/build/static/js/main.8bf4c404.js.LICENSE.txt
st_img_selector/frontend/build/static/js/main.8bf4c404.js.map
st_img_selector/frontend/build/static/js/main.f8049331.js
st_img_selector/frontend/build/static/js/main.f8049331.js.LICENSE.txt
st_img_selector/frontend/build/static/js/main.f8049331.js.map
st_img_selector-0.0.2.dist-info/LICENSE
st_img_selector-0.0.2.dist-info/METADATA
st_img_selector-0.0.2.dist-info/WHEEL
st_img_selector-0.0.2.dist-info/top_level.txt
st_img_selector-0.0.2.dist-info/RECORD
